MANIFEST.in
setup.cfg
setup.py
simplescn/__init__.py
simplescn/__main__.py
simplescn/_common.py
simplescn/_decos.py
simplescn/exceptions.py
simplescn/scnrequest.py
simplescn/server.py
simplescn.egg-info/PKG-INFO
simplescn.egg-info/SOURCES.txt
simplescn.egg-info/dependency_links.txt
simplescn.egg-info/entry_points.txt
simplescn.egg-info/requires.txt
simplescn.egg-info/top_level.txt
simplescn/client/__init__.py
simplescn/client/_client_admin.py
simplescn/client/_client_safe.py
simplescn/cmdcom/__init__.py
simplescn/cmdcom/__main__.py
simplescn/config/__init__.py
simplescn/config/parameters.py
simplescn/massimport/__init__.py
simplescn/massimport/__main__.py
simplescn/pwrequester/__init__.py
simplescn/pwrequester/cmdpw.py
simplescn/pwrequester/gtkpw.py
simplescn/pwrequester/kivypw.py
simplescn/pwrequester/qtpw.py
simplescn/tools/__init__.py
simplescn/tools/checks.py
simplescn/tools/start.py