Metadata-Version: 1.1
Name: simplescn
Version: 0.7.1
Summary: Simple communication nodes
Home-page: https://github.com/devkral/simplescn
Author: Alexander K.
Author-email: devkral@web.de
License: MIT
Download-URL: https://github.com/devkral/simplescn/tarball/0.7.1
Keywords: simplescn,scn
Platform: Platform Independent
Classifier: License :: OSI Approved :: MIT License
Classifier: Operating System :: OS Independent
Classifier: Programming Language :: Python :: 3.5
Classifier: Programming Language :: Python :: 3 :: Only
Classifier: Topic :: Communications
Classifier: Topic :: Internet
Classifier: Topic :: Security
